nats_kv_lock/__init__.py
nats_kv_lock/nats_kv_lock.py
nats_kv_lock/py.typed
nats_kv_lock-0.0.1.dist-info/METADATA
nats_kv_lock-0.0.1.dist-info/WHEEL
nats_kv_lock-0.0.1.dist-info/licenses/LICENSE
nats_kv_lock-0.0.1.dist-info/RECORD
