Metadata-Version: 2.4
Name: nats_kv_lock
Version: 0.0.1
Summary: Distributed lock using NATS.io
Project-URL: Homepage, https://github.com/kevinhikaruevans/nats-kv-lock
Project-URL: Issues, https://github.com/kevinhikaruevans/nats-kv-lock/issues
Author-email: Kevin Evans <evans.kevinh@gmail.com>
License-File: LICENSE
Classifier: License :: OSI Approved :: MIT License
Classifier: Operating System :: OS Independent
Classifier: Programming Language :: Python :: 3
Requires-Python: >=3.11
Requires-Dist: nats-py
